setup.py
stats_dist_prob_gb/Binomialdistribution.py
stats_dist_prob_gb/Gaussiandistribution.py
stats_dist_prob_gb/Generaldistribution.py
stats_dist_prob_gb/__init__.py
stats_dist_prob_gb.egg-info/PKG-INFO
stats_dist_prob_gb.egg-info/SOURCES.txt
stats_dist_prob_gb.egg-info/dependency_links.txt
stats_dist_prob_gb.egg-info/not-zip-safe
stats_dist_prob_gb.egg-info/top_level.txt