Metadata-Version: 1.0
Name: stats-dist-prob-gb
Version: 0.1
Summary: Gaussian and Binomial distributions
Home-page: UNKNOWN
Author: Erin Gill
Author-email: erin.gill81@gmail.com
License: UNKNOWN
Platform: UNKNOWN
